odoo8_addon_mgmtsystem_audit-8.0.1.2.0.99.dev11-nspkg.pth
odoo_addons/mgmtsystem_audit/README.rst
odoo_addons/mgmtsystem_audit/__init__.py
odoo_addons/mgmtsystem_audit/__openerp__.py
odoo_addons/mgmtsystem_audit/data/audit_sequence.xml
odoo_addons/mgmtsystem_audit/demo/demo_audit.xml
odoo_addons/mgmtsystem_audit/i18n/de.po
odoo_addons/mgmtsystem_audit/i18n/es.po
odoo_addons/mgmtsystem_audit/i18n/fr.po
odoo_addons/mgmtsystem_audit/i18n/hr.po
odoo_addons/mgmtsystem_audit/i18n/id.po
odoo_addons/mgmtsystem_audit/i18n/mgmtsystem_audit.pot
odoo_addons/mgmtsystem_audit/i18n/nb.po
odoo_addons/mgmtsystem_audit/i18n/nl.po
odoo_addons/mgmtsystem_audit/i18n/nn.po
odoo_addons/mgmtsystem_audit/i18n/pt_BR.po
odoo_addons/mgmtsystem_audit/i18n/sl.po
odoo_addons/mgmtsystem_audit/i18n/sv.po
odoo_addons/mgmtsystem_audit/i18n/vi.po
odoo_addons/mgmtsystem_audit/migrations/7.0.1.0/openupgrade_analysis.txt
odoo_addons/mgmtsystem_audit/migrations/7.0.1.0/post-migration.py
odoo_addons/mgmtsystem_audit/models/__init__.py
odoo_addons/mgmtsystem_audit/models/mgmtsystem_audit.py
odoo_addons/mgmtsystem_audit/report/__init__.py
odoo_addons/mgmtsystem_audit/report/audit_report.py
odoo_addons/mgmtsystem_audit/report/audit_report.rml
odoo_addons/mgmtsystem_audit/report/audit_report.xml
odoo_addons/mgmtsystem_audit/report/verification_list.py
odoo_addons/mgmtsystem_audit/report/verification_list.rml
odoo_addons/mgmtsystem_audit/report/verification_list.xml
odoo_addons/mgmtsystem_audit/security/ir.model.access.csv
odoo_addons/mgmtsystem_audit/security/mgmtsystem_audit_security.xml
odoo_addons/mgmtsystem_audit/static/description/icon.png
odoo_addons/mgmtsystem_audit/views/board_mgmtsystem_audit.xml
odoo_addons/mgmtsystem_audit/views/mgmtsystem_audit.xml
odoo_addons/mgmtsystem_audit/wizard/__init__.py
odoo_addons/mgmtsystem_audit/wizard/copy_verification_lines.py
odoo_addons/mgmtsystem_audit/wizard/copy_verification_lines.xml
odoo8_addon_mgmtsystem_audit-8.0.1.2.0.99.dev11.dist-info/METADATA
odoo8_addon_mgmtsystem_audit-8.0.1.2.0.99.dev11.dist-info/WHEEL
odoo8_addon_mgmtsystem_audit-8.0.1.2.0.99.dev11.dist-info/namespace_packages.txt
odoo8_addon_mgmtsystem_audit-8.0.1.2.0.99.dev11.dist-info/top_level.txt
odoo8_addon_mgmtsystem_audit-8.0.1.2.0.99.dev11.dist-info/RECORD
