Metadata-Version: 2.1
Name: odoo8-addon-mgmtsystem-audit
Version: 8.0.1.2.0.99.dev11
Summary: Management System - Audit
Home-page: http://www.savoirfairelinux.com
Author: Savoir-faire Linux, Odoo Community Association (OCA)
Author-email: support@odoo-community.org
License: AGPL-3
Platform: UNKNOWN
Classifier: Programming Language :: Python
Classifier: Framework :: Odoo
Classifier: License :: OSI Approved :: GNU Affero General Public License v3
Requires-Python: ~=2.7
Requires-Dist: odoo8-addon-mgmtsystem-nonconformity
Requires-Dist: odoo (<9.0a,>=8.0a)
